MANIFEST.in
README.rst
setup.py
trialosxnotifier.py
trial_osxnotifier.egg-info/PKG-INFO
trial_osxnotifier.egg-info/SOURCES.txt
trial_osxnotifier.egg-info/dependency_links.txt
trial_osxnotifier.egg-info/requires.txt
trial_osxnotifier.egg-info/top_level.txt
twisted/plugins/dropin.cache
twisted/plugins/trial_osxnotify.py